pdtr/__init__.py
pdtr/excel_writer.py
pdtr/matplot_chinese.ttf
pdtr/template.xlsx
pdtr/transforme.py
pdtr-0.1.5.dist-info/LICENSE
pdtr-0.1.5.dist-info/METADATA
pdtr-0.1.5.dist-info/WHEEL
pdtr-0.1.5.dist-info/top_level.txt
pdtr-0.1.5.dist-info/RECORD
