Metadata-Version: 2.1
Name: pdtr
Version: 0.1.5
Summary: 自动决策树规则挖掘工具包
Home-page: https://github.com/itlubber/pdtr
Author: itlubber
Author-email: itlubber@qq.com
License: MIT
Classifier: Operating System :: POSIX
Classifier: Operating System :: Microsoft :: Windows
Classifier: Operating System :: MacOS :: MacOS X
Classifier: Programming Language :: Python :: 3.6
Classifier: Programming Language :: Python :: 3.7
Classifier: Programming Language :: Python :: 3.8
Classifier: Programming Language :: Python :: 3.9
Classifier: Programming Language :: Python :: 3.10
Requires-Python: >=3.6
License-File: LICENSE
Requires-Dist: wget
Requires-Dist: scorecardpipeline
Requires-Dist: category-encoders (>=2.6.0)
Requires-Dist: statsmodels (<0.14,>=0.13.2)
Requires-Dist: CairoSVG (>=2.7.0)
Requires-Dist: graphviz (>=0.20.1)
Requires-Dist: dtreeviz (>=2.2.1)
Requires-Dist: reportlab
Requires-Dist: svglib
